pymm_eventserver/PythonEventServer.jar
pymm_eventserver/data_structures.py
pymm_eventserver/event_thread.py
pymm_eventserver/settings.json
pymm_eventserver/setup.py
pymm_eventserver-0.1.19.dist-info/LICENSE
pymm_eventserver-0.1.19.dist-info/METADATA
pymm_eventserver-0.1.19.dist-info/WHEEL
pymm_eventserver-0.1.19.dist-info/top_level.txt
pymm_eventserver-0.1.19.dist-info/RECORD
