Metadata-Version: 2.1
Name: pymm-eventserver
Version: 0.1.19
Summary: Micro-Manager PythonEventServer
Home-page: https://github.com/leb-epfl/pymm-eventserver
Author: Willi L. Stepp
Author-email: willi.stepp@epfl.ch
Project-URL: Bug Tracker, https://github.com/leb-epfl/pymm-eventserver/issues
Classifier: Programming Language :: Python :: 3
Classifier: License :: OSI Approved :: BSD License
Classifier: Operating System :: OS Independent
Requires-Python: >=3.7
License-File: LICENSE
Requires-Dist: pycromanager
Requires-Dist: qtpy
